<?xml version='1.0' encoding='UTF-8'?>
<Chroma>
  <English/>
  <繁體中文>
    <Message Name="Rollback" Value="復原"/>
    <Message Name="Query" Value="查詢"/>
    <Message Name="Rework No" Value="重工單號"/>
    <Message Name="Serial Number" Value="序號"/>
    <Message Name="Work Order" Value="工單"/>
    <Message Name="PDLine" Value="生產線"/>
    <Message Name="WIP Process" Value="WIP製程"/>
    <Message Name="Process Name" Value="製程別"/>
    <Message Name="Terminal" Value="工作站"/>
    <Message Name="Customer SN" Value="出貨序號"/>
    <Message Name="Pallet No" Value="棧板號"/>
    <Message Name="Carton No" Value="箱號"/>
    <Message Name="Status" Value="狀態"/>
    <Message Name="S/N" Value="序號"/>
    <Message Name="Count" Value="筆數"/>
    <Message Name="Are you sure to Rollback ?" Value="確定要執行復原作業 ?"/>
    <Message Name="Please Input Rework No!" Value="請輸入重工單號"/>
    <Message Name="Error" Value="錯誤"/>
    <Message Name="All S/N Start Rework Route , Can't Rollback!" Value="所有產品已投入重工途程,不可復原"/>
    <Message Name="pieces already Start Rework Route" Value="片已投入重工途程"/>
    <Message Name="Sure to Rollback other Serial Number" Value="確定要繼續進行其他序號的復原"/>
    <Message Name="No Choose S/N" Value="請勾選要復原的序號"/>
  </繁體中文>
  <简体中文>
    <Message Name="Rollback" Value="复原"/>
    <Message Name="Query" Value="查询"/>
    <Message Name="Rework No" Value="重工单号"/>
    <Message Name="Serial Number" Value="序号"/>
    <Message Name="Work Order" Value="工单"/>
    <Message Name="PDLine" Value="生产线"/>
    <Message Name="WIP Process" Value="WIP制程"/>
    <Message Name="Process Name" Value="制程别"/>
    <Message Name="Terminal" Value="工作站"/>
    <Message Name="Customer SN" Value="出货序号"/>
    <Message Name="Pallet No" Value="栈板号"/>
    <Message Name="Carton No" Value="箱号"/>
    <Message Name="Status" Value="状态"/>
    <Message Name="S/N" Value="序号"/>
    <Message Name="Count" Value="笔数"/>
    <Message Name="Are you sure to Rollback ?" Value="确定要执行复原作业 ?"/>
    <Message Name="Please Input Rework No!" Value="请输入重工单号"/>
    <Message Name="Error" Value="错误"/>
    <Message Name="All S/N Start Rework Route , Can't Rollback!" Value="所有产品已投入重工途程,不可复原"/>
    <Message Name="pieces already Start Rework Route" Value="片已投入重工途程"/>
    <Message Name="Sure to Rollback other Serial Number" Value="确定要继续进行其他序号的复原"/>
    <Message Name="No Choose S/N" Value="请勾选要复原的序号"/>
  </简体中文>
<Ngôn_ngữ_Việt><Message Name="Rollback" Value="Khôi phục"/><Message Name="Query" Value="Truy vấn"/><Message Name="Rework No" Value="Mã đơn tái công"/><Message Name="Serial Number" Value="Số seri"/><Message Name="Work Order" Value="Lệnh sản xuất"/><Message Name="PDLine" Value="Dây chuyền"/><Message Name="WIP Process" Value="Công đoạn WIP"/><Message Name="Process Name" Value="Loại công đoạn"/><Message Name="Terminal" Value="Trạm làm việc"/><Message Name="Customer SN" Value="Số seri xuất hàng"/><Message Name="Pallet No" Value="Mã pallet"/><Message Name="Carton No" Value="Mã thùng"/><Message Name="Status" Value="Trạng thái"/><Message Name="S/N" Value="Số seri"/><Message Name="Count" Value="Số lượng"/><Message Name="Are you sure to Rollback ?" Value="Bạn có chắc muốn khôi phục không?"/><Message Name="Please Input Rework No!" Value="Vui lòng nhập mã đơn tái công!"/><Message Name="Error" Value="Lỗi"/><Message Name="All S/N Start Rework Route , Can't Rollback!" Value="Tất cả số seri đã vào tuyến tái công, không thể khôi phục!"/><Message Name="pieces already Start Rework Route" Value=" sản phẩm đã vào tuyến tái công"/><Message Name="Sure to Rollback other Serial Number" Value="Bạn có chắc muốn tiếp tục khôi phục các số seri khác?"/><Message Name="No Choose S/N" Value="Vui lòng chọn số seri cần khôi phục"/></Ngôn_ngữ_Việt></Chroma>
